README.md
setup.py
srap/__init__.py
srap.egg-info/PKG-INFO
srap.egg-info/SOURCES.txt
srap.egg-info/dependency_links.txt
srap.egg-info/top_level.txt