Metadata-Version: 1.0
Name: srap
Version: 0.1.0
Summary: Simple reflect annotation protocol lib.
Home-page: https://github.com/aozhiwei/srap
Author: Zhiwei Ao
Author-email: 164439244@qq.com
License: MIT License
